odoo/addons/web_ir_actions_act_view_reload/README.rst
odoo/addons/web_ir_actions_act_view_reload/__init__.py
odoo/addons/web_ir_actions_act_view_reload/__manifest__.py
odoo/addons/web_ir_actions_act_view_reload/i18n/web_ir_actions_act_view_reload.pot
odoo/addons/web_ir_actions_act_view_reload/static/description/icon.png
odoo/addons/web_ir_actions_act_view_reload/static/src/js/web_ir_actions_act_view_reload.js
odoo/addons/web_ir_actions_act_view_reload/views/web_ir_actions_act_view_reload.xml
odoo11_addon_web_ir_actions_act_view_reload-11.0.1.0.1.dist-info/METADATA
odoo11_addon_web_ir_actions_act_view_reload-11.0.1.0.1.dist-info/WHEEL
odoo11_addon_web_ir_actions_act_view_reload-11.0.1.0.1.dist-info/top_level.txt
odoo11_addon_web_ir_actions_act_view_reload-11.0.1.0.1.dist-info/RECORD
